metacrawler/pagination.py
metacrawler/crawlers.py
metacrawler/authentication.py
metacrawler/__init__.py
metacrawler/items.py
metacrawler/commands.py
metacrawler/base.py
metacrawler/settings.py
metacrawler/handlers.py
metacrawler/fields.py
metacrawler/template/run.py
metacrawler/template/settings.config
metacrawler/template/elements/crawlers.py
metacrawler/template/elements/__init__.py
metacrawler/template/elements/constants.py
metacrawler/template/elements/settings.py
metacrawler/template/elements/handlers.py
metacrawler/template/elements/fields.py
metacrawler-0.3.3.dist-info/top_level.txt
metacrawler-0.3.3.dist-info/entry_points.txt
metacrawler-0.3.3.dist-info/WHEEL
metacrawler-0.3.3.dist-info/METADATA
metacrawler-0.3.3.dist-info/RECORD
metacrawler-0.3.3.dist-info/metadata.json
metacrawler-0.3.3.dist-info/DESCRIPTION.rst
